pytest_documentary/__init__.py
pytest_documentary/plugin.py
pytest_documentary-0.1.0.dist-info/METADATA
pytest_documentary-0.1.0.dist-info/WHEEL
pytest_documentary-0.1.0.dist-info/entry_points.txt
pytest_documentary-0.1.0.dist-info/top_level.txt
pytest_documentary-0.1.0.dist-info/RECORD
