Metadata-Version: 2.1
Name: pytest-documentary
Version: 0.1.0
Summary: A simple pytest plugin to generate test documentation
Classifier: Framework :: Pytest
Requires-Dist: pytest
Requires-Dist: pandas
Requires-Dist: openpyxl
